LICENSE
MANIFEST.in
README.rst
setup.py
mfcloud/__init__.py
mfcloud/api.py
mfcloud/application.py
mfcloud/attach.py
mfcloud/config.py
mfcloud/container.py
mfcloud/deployment.py
mfcloud/dns_resolver.py
mfcloud/events.py
mfcloud/metadata.py
mfcloud/remote.py
mfcloud/rpc_client.py
mfcloud/rpc_server.py
mfcloud/service.py
mfcloud/shell.py
mfcloud/ssl.py
mfcloud/tasks.py
mfcloud/test_utils.py
mfcloud/txdocker.py
mfcloud/txhttp.py
mfcloud/util.py
mfcloud.egg-info/PKG-INFO
mfcloud.egg-info/SOURCES.txt
mfcloud.egg-info/dependency_links.txt
mfcloud.egg-info/entry_points.txt
mfcloud.egg-info/not-zip-safe
mfcloud.egg-info/requires.txt
mfcloud.egg-info/top_level.txt
mfcloud/plugins/__init__.py
mfcloud/plugins/dns.py
mfcloud/plugins/haproxy.py
mfcloud/plugins/hosts.py
mfcloud/plugins/internal_api.py
mfcloud/plugins/metrics.py
mfcloud/plugins/monitor.py
mfcloud/sync/__init__.py
mfcloud/sync/client.py
mfcloud/sync/diff.py
mfcloud/sync/server.py
mfcloud/sync/storage.py
mfcloud/sync/transfer.py
mfcloud/sync/utils.py